Metadata-Version: 2.1
Name: sgui
Version: 0.1.3
Summary: A simple GUI library for Python
Home-page: https://github.com/DGriffin91/sgui
Author: DGriffin91
Author-email: sgui@dgdigital.net
License: MIT
Platform: UNKNOWN
